nonebot_plugin_daily_oil_price/__init__.py
nonebot_plugin_daily_oil_price/config.py
nonebot_plugin_daily_oil_price/utils.py
nonebot_plugin_daily_oil_price-0.1.3.dist-info/LICENSE
nonebot_plugin_daily_oil_price-0.1.3.dist-info/METADATA
nonebot_plugin_daily_oil_price-0.1.3.dist-info/WHEEL
nonebot_plugin_daily_oil_price-0.1.3.dist-info/RECORD
