Metadata-Version: 2.1
Name: nonebot-plugin-daily-oil-price
Version: 0.1.3
Summary: nonebot每日油价插件
License: MIT
Author: wyeeeee
Author-email: 1563031828@qq.com
Requires-Python: >=3.10,<4.0
Classifier: License :: OSI Approved :: MIT License
Classifier: Programming Language :: Python :: 3
Classifier: Programming Language :: Python :: 3.10
Classifier: Programming Language :: Python :: 3.11
Classifier: Programming Language :: Python :: 3.12
Requires-Dist: httpx (>=0.27.0,<0.28.0)
Requires-Dist: nonebot-adapter-onebot (>=2.4.4,<3.0.0)
Requires-Dist: nonebot-plugin-apscheduler (>=0.5.0,<0.6.0)
Requires-Dist: nonebot-plugin-localstore (>=0.7.0,<0.8.0)
Requires-Dist: nonebot2 (>=2.3.2,<3.0.0)
